exohammer/__init__.py
exohammer/data.py
exohammer/mcmc_run.py
exohammer/planetary_system.py
exohammer/store.py
exohammer/system.py
exohammer/utilities.py
exohammer/version.py
exohammer/lnprob/__init__.py
exohammer/lnprob/initialize_prob.py
exohammer/lnprob/lnprob_both.py
exohammer/lnprob/lnprob_rv.py
exohammer/lnprob/lnprob_ttv.py
exohammer/model/__init__.py
exohammer/model/initialize_model.py
exohammer/model/model_both.py
exohammer/model/model_rv.py
exohammer/model/model_ttv.py
exohammer-0.1.0.dist-info/LICENSE
exohammer-0.1.0.dist-info/METADATA
exohammer-0.1.0.dist-info/WHEEL
exohammer-0.1.0.dist-info/top_level.txt
exohammer-0.1.0.dist-info/RECORD
