Metadata-Version: 2.1
Name: exohammer
Version: 0.1.0
Summary: TTV and RV MCMC generator
Home-page: https://github.com/nick-juliano/exohammer
Author: Nick Juliano
Author-email: nick_juliano@icloud.com
License: GPL
License-File: LICENSE
Requires-Dist: astropy (==4.0.1.post1)
Requires-Dist: corner (==2.1.0)
Requires-Dist: emcee (==3.0.2)
Requires-Dist: matplotlib (==3.2.2)
Requires-Dist: numpy (==1.19.5)
Requires-Dist: pandas (==1.0.5)
Requires-Dist: ttvfast (==0.3.0)
Requires-Dist: easygui (==0.98.3)
Provides-Extra: extras
Requires-Dist: pickle ; extra == 'extras'
Requires-Dist: matplotlib ; extra == 'extras'
Requires-Dist: easygui ; extra == 'extras'
